Customer-Scripts/EngineMonitor/EngineMonitor/EngineMonitor.py
Customer-Scripts/EngineVersion/EngineVersion.py
Customer-Scripts/ProcessFiles/ProcessFiles.py
Customer-Scripts/ProcessFiles/addrelativepath.py
GetPacket/get_packet.py
PyTest/PyTest.py
PyTest/addrelativepath.py
PyTest/omni_options.py
PyTest/omni_printers.py
omniscript/__init__.py
omniscript/adapter.py
omniscript/adapterinformation.py
omniscript/alarm.py
omniscript/analysismodule.py
omniscript/application.py
omniscript/applicationflowstatistic.py
omniscript/applicationstatistic.py
omniscript/auditlog.py
omniscript/authenticationtoken.py
omniscript/callstatistic.py
omniscript/capabilities.py
omniscript/capture.py
omniscript/capturesession.py
omniscript/capturetemplate.py
omniscript/conversationstatistic.py
omniscript/country.py
omniscript/countrystatistic.py
omniscript/decryptionkey.py
omniscript/decryptionkeytemplate.py
omniscript/directory.py
omniscript/enginesettings.py
omniscript/enginestatus.py
omniscript/errorstatistic.py
omniscript/eventlog.py
omniscript/expertpreferences.py
omniscript/fileinformation.py
omniscript/filter.py
omniscript/filternode.py
omniscript/forensicsearch.py
omniscript/forensictemplate.py
omniscript/graphtemplate.py
omniscript/helpers.py
omniscript/historystatistic.py
omniscript/invariant.py
omniscript/license.py
omniscript/liveflow.py
omniscript/mediainformation.py
omniscript/mediaspecification.py
omniscript/nametable.py
omniscript/networkstatistic.py
omniscript/nodestatistic.py
omniscript/notifications.py
omniscript/omniaddress.py
omniscript/omnidatatable.py
omniscript/omniengine.py
omniscript/omnierror.py
omniscript/omniid.py
omniscript/omniport.py
omniscript/omniscript.py
omniscript/packet.py
omniscript/packetfileinformation.py
omniscript/peektime.py
omniscript/performancelogger.py
omniscript/protocol.py
omniscript/protocolstatistic.py
omniscript/protocoltranslation.py
omniscript/readstream.py
omniscript/remoteengine.py
omniscript/selection.py
omniscript/sizestatistic.py
omniscript_liveaction-3.0.54.dist-info/licenses/LICENSE
omniscript_liveaction-3.0.54.dist-info/METADATA
omniscript_liveaction-3.0.54.dist-info/WHEEL
omniscript_liveaction-3.0.54.dist-info/top_level.txt
omniscript_liveaction-3.0.54.dist-info/RECORD
