Metadata-Version: 2.4
Name: omniscript-liveaction
Version: 3.0.54
Summary: Automate LiveAction LiveCapture and LiveWire.
Home-page: https://MyPeek.LiveAction.com
Author: gvisser
Author-email: gvisser@liveaction.com
Project-URL: Bug Tracker, https://MyPeek.LiveAction.com
Classifier: Programming Language :: Python :: 3
Classifier: License :: OSI Approved :: MIT License
Classifier: Operating System :: OS Independent
Requires-Python: >=3.8
License-File: LICENSE
Requires-Dist: requests
Requires-Dist: urllib3
Dynamic: license-file
